shipyard_googledocs/__init__.py
shipyard_googledocs/exceptions.py
shipyard_googledocs/googledocs.py
shipyard_googledocs/cli/__init__.py
shipyard_googledocs/cli/authtest.py
shipyard_googledocs/cli/download.py
shipyard_googledocs-0.1.0.dist-info/METADATA
shipyard_googledocs-0.1.0.dist-info/WHEEL
shipyard_googledocs-0.1.0.dist-info/top_level.txt
shipyard_googledocs-0.1.0.dist-info/RECORD
