Metadata-Version: 2.4
Name: shipyard-googledocs
Version: 0.1.0
Summary: A local client for connecting and working with Google Docs
Requires-Python: >=3.11
Requires-Dist: google-api-python-client>=2.169.0
Requires-Dist: google-auth-httplib2>=0.2.0
Requires-Dist: google-auth-oauthlib>=1.2.2
Requires-Dist: shipyard-bp-utils>=1.3.2
Requires-Dist: shipyard-templates>=0.10.0
